<?xml version="1.0" encoding="us-ascii"?>
<Catalog>
    <CWeaponLegacy id="GuassRifle">
        <Range value="4.6"/>
    </CWeaponLegacy>
    <CWeaponLegacy id="HammerSecurity">
        <Range value="4.8"/>
    </CWeaponLegacy>
    <CWeaponLegacy id="KelmorianMinerGaussRifle">
        <Range value="4.6"/>
    </CWeaponLegacy>
    <CWeaponLegacy id="MercReaperP38ScytheGuassPistol">
        <Range value="4.3"/>
    </CWeaponLegacy>
    <CWeaponLegacy id="P38ScytheGuassPistol">
        <Range value="4.3"/>
    </CWeaponLegacy>
    <CWeaponLegacy id="PunisherGrenades">
        <Range value="4.8"/>
    </CWeaponLegacy>
</Catalog>
